mcp_server_spider/__init__.py
mcp_server_spider/__main__.py
mcp_server_spider/server.py
mcp_server_spider-0.1.0.dist-info/METADATA
mcp_server_spider-0.1.0.dist-info/WHEEL
mcp_server_spider-0.1.0.dist-info/entry_points.txt
mcp_server_spider-0.1.0.dist-info/licenses/LICENSE
mcp_server_spider-0.1.0.dist-info/RECORD
