Metadata-Version: 2.4
Name: mcp-server-spider
Version: 0.1.0
Summary: A Model Context Protocol server providing tools to execute spider crawler
Author: George Liontos
Maintainer-email: George Liontos <georgeliontos98@gmail.com>
License: MIT
License-File: LICENSE
Keywords: automation,crawler,llm,mcp,spider_rs
Classifier: Development Status :: 4 - Beta
Classifier: Intended Audience :: Developers
Classifier: License :: OSI Approved :: MIT License
Classifier: Programming Language :: Python :: 3
Classifier: Programming Language :: Python :: 3.13
Requires-Python: >=3.13
Requires-Dist: mcp>=1.6.0
Requires-Dist: pydantic>=2.11.3
Requires-Dist: spider-rs>=0.0.57
